pycord_components/__init__.py
pycord_components/client.py
pycord_components/component.py
pycord_components/const.py
pycord_components/dpy_overrides.py
pycord_components/http.py
pycord_components/interaction.py
pycord_components/utils.py
pycord_components/ext/filters.py
pycord_components-1.0.2.dist-info/LICENSE
pycord_components-1.0.2.dist-info/METADATA
pycord_components-1.0.2.dist-info/WHEEL
pycord_components-1.0.2.dist-info/top_level.txt
pycord_components-1.0.2.dist-info/RECORD
