Metadata-Version: 2.1
Name: pycord-components
Version: 1.0.2
Summary: An unofficial library for pycord components.
Home-page: https://github.com/Leek5/pycord-components
Author: Leek5
Author-email: gyubini38@protonmail.com
License: MIT License
Platform: UNKNOWN
Classifier: Intended Audience :: Developers
Classifier: License :: OSI Approved :: MIT License
Classifier: Natural Language :: English
Classifier: Operating System :: OS Independent
Classifier: Programming Language :: Python :: 3
Classifier: Programming Language :: Python :: 3.6
Classifier: Programming Language :: Python :: 3.7
Classifier: Programming Language :: Python :: 3.8
Classifier: Programming Language :: Python :: 3.9
Classifier: Topic :: Internet
Classifier: Topic :: Software Development :: Libraries :: Python Modules
Classifier: Topic :: Software Development :: Libraries
Classifier: Topic :: Utilities
Requires-Python: >=3.6
License-File: LICENSE
Requires-Dist: py-cord
Requires-Dist: aiohttp
Provides-Extra: dev
Requires-Dist: black ; extra == 'dev'
Requires-Dist: flake8 ; extra == 'dev'
Requires-Dist: isort ; extra == 'dev'
Requires-Dist: sphinx ; extra == 'dev'
Requires-Dist: sphinx-rtd-theme ; extra == 'dev'
Provides-Extra: lint
Requires-Dist: black ; extra == 'lint'
Requires-Dist: flake8 ; extra == 'lint'
Requires-Dist: isort ; extra == 'lint'
Requires-Dist: sphinx ; extra == 'lint'
Requires-Dist: sphinx-rtd-theme ; extra == 'lint'
Provides-Extra: readthedocs
Requires-Dist: sphinx ; extra == 'readthedocs'
Requires-Dist: sphinx-rtd-theme ; extra == 'readthedocs'
